DTPySide/DT.qrc
DTPySide/DTAPP.py
DTPySide/DTFunction.py
DTPySide/DTStyleSheet.py
DTPySide/DT_rc.py
DTPySide/__init__.py
DTPySide/deepGenerateTsFile.py
DTPySide/deepUpdateUiFile.py
DTPySide/DTFrame/DTDialog.py
DTPySide/DTFrame/DTDialogLinux.py
DTPySide/DTFrame/DTDialogWin32.py
DTPySide/DTFrame/DTMainWindow.py
DTPySide/DTFrame/DTMainWindowLinux.py
DTPySide/DTFrame/DTMainWindowWin32.py
DTPySide/DTFrame/DTMessageBox.py
DTPySide/DTFrame/Ui_DTDialogLinux.py
DTPySide/DTFrame/Ui_DTDialogLinux.ui
DTPySide/DTFrame/Ui_DTDialogWin32.py
DTPySide/DTFrame/Ui_DTDialogWin32.ui
DTPySide/DTFrame/Ui_DTMainWindowLinux.py
DTPySide/DTFrame/Ui_DTMainWindowLinux.ui
DTPySide/DTFrame/Ui_DTMainWindowWin32.py
DTPySide/DTFrame/Ui_DTMainWindowWin32.ui
DTPySide/DTFrame/Ui_DTMessageBox.py
DTPySide/DTFrame/Ui_DTMessageBox.ui
DTPySide/DTFrame/__init__.py
DTPySide/DTIcon/__init__.py
DTPySide/DTModule/DTLogin.py
DTPySide/DTModule/DTSetting.py
DTPySide/DTModule/Ui_DTLogin.py
DTPySide/DTModule/Ui_DTLogin.ui
DTPySide/DTModule/Ui_DTSetting.py
DTPySide/DTModule/Ui_DTSetting.ui
DTPySide/DTModule/__init__.py
DTPySide/DTSession/DTLoginSession.py
DTPySide/DTSession/DTMainSession.py
DTPySide/DTSession/DTSettingSession.py
DTPySide/DTSession/__init__.py
DTPySide/DTTranslation/__init__.py
DTPySide/DTTranslation/en.qm
DTPySide/DTTranslation/en.ts
DTPySide/DTTranslation/eo.qm
DTPySide/DTTranslation/eo.ts
DTPySide/DTTranslation/ja.qm
DTPySide/DTTranslation/ja.ts
DTPySide/DTTranslation/jp.ts
DTPySide/DTTranslation/lreleaseRootTsFile.py
DTPySide/DTTranslation/ru.qm
DTPySide/DTTranslation/ru.ts
DTPySide/DTTranslation/zh_CN.qm
DTPySide/DTTranslation/zh_CN.ts
DTPySide/DTTranslation/zh_TW.qm
DTPySide/DTTranslation/zh_TW.ts
DTPySide/DTWidget/DTApplyButton.py
DTPySide/DTWidget/DTCapsuleButton.py
DTPySide/DTWidget/DTDockWidget.py
DTPySide/DTWidget/DTDockWidgetLinux.py
DTPySide/DTWidget/DTDockWidgetWin32.py
DTPySide/DTWidget/DTHorizontalTabel.py
DTPySide/DTWidget/DTLine.py
DTPySide/DTWidget/DTPlainTextEdit.py
DTPySide-0.1.9.dist-info/LICENSE
DTPySide-0.1.9.dist-info/METADATA
DTPySide-0.1.9.dist-info/WHEEL
DTPySide-0.1.9.dist-info/top_level.txt
DTPySide-0.1.9.dist-info/RECORD
