Metadata-Version: 2.1
Name: DTPySide
Version: 0.1.9
Summary: A PySide framework for constructing customizable GUI software.
Home-page: https://github.com/Holence/DTPySide
Author: Holence
Author-email: Holence08@gmail.com
Project-URL: Bug Tracker, https://github.com/Holence/DTPySide/issues
Classifier: Programming Language :: Python :: 3
Classifier: License :: OSI Approved :: MIT License
Classifier: Operating System :: OS Independent
Requires-Python: >=3.8
License-File: LICENSE
Requires-Dist: colour
Requires-Dist: cryptography
Requires-Dist: pypinyin
Requires-Dist: PySide2
Requires-Dist: send2trash
Requires-Dist: blosc
